datadict_connector_mysql/__init__.py
datadict_connector_mysql/mysql.py
datadict_connector_mysql/mysql_source.py
datadict_connector_mysql-0.0.2.dist-info/METADATA
datadict_connector_mysql-0.0.2.dist-info/WHEEL
datadict_connector_mysql-0.0.2.dist-info/top_level.txt
datadict_connector_mysql-0.0.2.dist-info/RECORD
